slicer/__init__.py
slicer/slicer.py
slicer/slicer_internal.py
slicer/test_slicer.py
slicer/utils_testing.py
slicer-0.0.6.dist-info/LICENSE
slicer-0.0.6.dist-info/METADATA
slicer-0.0.6.dist-info/WHEEL
slicer-0.0.6.dist-info/top_level.txt
slicer-0.0.6.dist-info/RECORD
