Metadata-Version: 2.1
Name: slicer
Version: 0.0.6
Summary: A small package for big slicing.
Home-page: https://github.com/interpretml/slicer
Author: InterpretML
Author-email: interpret@microsoft.com
License: UNKNOWN
Platform: UNKNOWN
Classifier: Programming Language :: Python :: 3.6
Classifier: Programming Language :: Python :: 3.7
Classifier: Programming Language :: Python :: 3.8
Classifier: Development Status :: 3 - Alpha
Classifier: License :: OSI Approved :: MIT License
Classifier: Operating System :: OS Independent
Requires-Python: >=3.6
